wuddz_lit/lit.py
wuddz_lit-1.0.8.dist-info/METADATA
wuddz_lit-1.0.8.dist-info/WHEEL
wuddz_lit-1.0.8.dist-info/entry_points.txt
wuddz_lit-1.0.8.dist-info/licenses/LICENSE
wuddz_lit-1.0.8.dist-info/RECORD
