Metadata-Version: 2.4
Name: wuddz_lit
Version: 1.0.8
Summary: Wuddz-Lit Is An Awesome & Quite Efficient Literotica.com Author/Category/Audio/Illustration Stories Downloader & Search.
Project-URL: Homepage, https://github.com/wuddz-devs/wuddz-lit
Author-email: Wuddz-Devs <wuddz_devs@protonmail.com>
License: MIT License
License-File: LICENSE
Keywords: audio,download,downloader,erotic,html,image,lit,literature,literotica,python,stories,story,text
Classifier: License :: OSI Approved :: MIT License
Classifier: Programming Language :: Python
Classifier: Programming Language :: Python :: 3.6
Classifier: Programming Language :: Python :: 3.7
Classifier: Programming Language :: Python :: 3.8
Classifier: Programming Language :: Python :: 3.9
Classifier: Programming Language :: Python :: 3.10
Requires-Python: >=3.6
Requires-Dist: requests
